blockbee/__init__.py
blockbee/admin.py
blockbee/apikey.py
blockbee/blockbee.py
blockbee/choices.py
blockbee/dispatchers.py
blockbee/forms.py
blockbee/meta.py
blockbee/models.py
blockbee/settings.py
blockbee/signals.py
blockbee/urls.py
blockbee/utils.py
blockbee/views.py
blockbee/migrations/0001_initial.py
blockbee/migrations/__init__.py
blockbee/templatetags/__init__.py
blockbee/templatetags/blockbee_helper.py
django_store/__init__.py
django_store/asgi.py
django_store/settings.py
django_store/urls.py
django_store/wsgi.py
store/__init__.py
store/admin.py
store/apps.py
store/forms.py
store/models.py
store/tests.py
store/urls.py
store/views.py
store/migrations/__init__.py
django_blockbee-1.0.1.dist-info/LICENSE
django_blockbee-1.0.1.dist-info/METADATA
django_blockbee-1.0.1.dist-info/WHEEL
django_blockbee-1.0.1.dist-info/top_level.txt
django_blockbee-1.0.1.dist-info/RECORD
