Metadata-Version: 2.1
Name: django-blockbee
Version: 1.0.1
Summary: Django implementation of BlockBee's payment gateway
Home-page: https://github.com/blockbee-io/django-blockbee
Author: BlockBee
Author-email: info@blockbee.io
License: MIT
Platform: UNKNOWN
Classifier: Programming Language :: Python
Classifier: Development Status :: 5 - Production/Stable
Classifier: Framework :: Django
Classifier: Intended Audience :: Developers
Classifier: License :: OSI Approved :: MIT License
Classifier: Natural Language :: English
Classifier: Operating System :: OS Independent
Classifier: Programming Language :: Python :: 3
License-File: LICENSE
Requires-Dist: django
Requires-Dist: requests
